Subdora/__init__.py
Subdora/_subdora.py
Subdora/_subdora_cli.py
Subdora/corex64/linux/Subdora.so
Subdora/corex64/win/Subdora.dll
Subdora/corex64/win/concrt140.dll
Subdora/corex64/win/libsodium.dll
Subdora/corex64/win/msvcp140.dll
Subdora/corex64/win/msvcp140_1.dll
Subdora/corex64/win/msvcp140_2.dll
Subdora/corex64/win/msvcp140_atomic_wait.dll
Subdora/corex64/win/msvcp140_codecvt_ids.dll
Subdora/corex64/win/vcamp140.dll
Subdora/corex64/win/vccorlib140.dll
Subdora/corex64/win/vcomp140.dll
Subdora/corex64/win/vcruntime140.dll
Subdora/corex64/win/vcruntime140_1.dll
Subdora/corex64/win/vcruntime140_threads.dll
Subdora-0.2.2.dist-info/METADATA
Subdora-0.2.2.dist-info/WHEEL
Subdora-0.2.2.dist-info/entry_points.txt
Subdora-0.2.2.dist-info/top_level.txt
Subdora-0.2.2.dist-info/RECORD
