Metadata-Version: 2.1
Name: Subdora
Version: 0.2.2
Summary: Subdora : A python package that takes care of obfuscation of python scripts
Home-page: https://github.com/Lakshit-Karsoliya/Subdora
Author: Lakshit Karsoliya
Author-email: lakshitkumar220@gmail.com
Keywords: python,file encryption,security,obfuscation
Classifier: Intended Audience :: Developers
Classifier: Programming Language :: Python :: 3
Classifier: Operating System :: Unix
Classifier: Operating System :: Microsoft :: Windows
Requires-Dist: pillow
